asyncio_tokenized_lock/__init__.py
asyncio_tokenized_lock/lock.py
asyncio_tokenized_lock-0.1.3.dist-info/LICENSE
asyncio_tokenized_lock-0.1.3.dist-info/METADATA
asyncio_tokenized_lock-0.1.3.dist-info/WHEEL
asyncio_tokenized_lock-0.1.3.dist-info/RECORD
