Metadata-Version: 2.1
Name: asyncio-tokenized-lock
Version: 0.1.3
Summary: A Python library providing token-based locking for efficient coordination of asynchronous tasks in asyncio.
Home-page: https://github.com/lucascicco/asyncio-tokenized-lock
License: MIT
Keywords: asyncio,lock,token,concurrency
Author: Lucas Cicco
Author-email: lucasciccomy@gmail.com
Maintainer: Lucas Cicco
Maintainer-email: lucasciccomy@gmail.com
Requires-Python: >=3.9,<4.0
Classifier: Development Status :: 3 - Alpha
Classifier: Intended Audience :: Developers
Classifier: License :: OSI Approved :: MIT License
Classifier: Operating System :: OS Independent
Classifier: Programming Language :: Python
Classifier: Programming Language :: Python :: 3
Classifier: Programming Language :: Python :: 3.9
Classifier: Programming Language :: Python :: 3.10
Classifier: Programming Language :: Python :: 3.11
Classifier: Programming Language :: Python :: 3.12
Project-URL: Repository, https://github.com/lucascicco/asyncio-tokenized-lock
